pyrip/__init__.py
pyrip/band.py
pyrip/calc.py
pyrip/cloud.py
pyrip/cog.py
pyrip/image.py
pyrip/interpolate.py
pyrip/plot.py
pyrip/transform.py
pyrip/util.py
pyrip/version.py
pyrip/warp.py
pyrip-1.5.9.dist-info/LICENSE
pyrip-1.5.9.dist-info/METADATA
pyrip-1.5.9.dist-info/WHEEL
pyrip-1.5.9.dist-info/top_level.txt
pyrip-1.5.9.dist-info/RECORD
