Metadata-Version: 2.1
Name: pyrip
Version: 1.5.9
Summary: Raster Image Processor - a thin wrap that provides some convenient functions over gdal
Home-page: https://github.com/lchu-ibm/pyrip
Author: Linsong Chu
Author-email: lchu@us.ibm.com
License: UNKNOWN
Platform: UNKNOWN
License-File: LICENSE
Requires-Dist: rasterio
Requires-Dist: pandas
Requires-Dist: numpy
Requires-Dist: shapely
Requires-Dist: pyproj
